{
  "_class": "sharedStyle",
  "do_objectID": "542AE31D-AB7C-455A-AA0C-B0D4B5700983",
  "name": "danger",
  "value": {
    "_class": "style",
    "endDecorationType": 0,
    "fills": [
      {
        "_class": "fill",
        "color": {
          "_class": "color",
          "alpha": 1,
          "blue": 0.0980392156862745,
          "green": 0.1098039215686275,
          "red": 1
        },
        "fillType": 0,
        "isEnabled": true,
        "noiseIndex": 0,
        "noiseIntensity": 0,
        "patternFillType": 1,
        "patternTileScale": 1
      }
    ],
    "miterLimit": 10,
    "sharedObjectID": "542AE31D-AB7C-455A-AA0C-B0D4B5700983",
    "startDecorationType": 0
  }
}