{
  "_class": "bitmap",
  "clippingMask": "{{0, 0}, {1, 1}}",
  "do_objectID": "FCB02083-1E17-4299-AB95-6BDC1C3E2162",
  "exportOptions": {
    "_class": "exportOptions",
    "exportFormats": [
    ],
    "includedLayerIds": [
    ],
    "layerOptions": 0,
    "shouldTrim": false
  },
  "fillReplacesImage": false,
  "frame": {
    "_class": "rect",
    "constrainProportions": true,
    "height": 16,
    "width": 22,
    "x": 22,
    "y": 26
  },
  "image": {
    "_class": "MSJSONFileReference",
    "_ref": "images/f1db006b00089ea82eb01dfed69f9a58e0d7d6fd",
    "_ref_class": "MSImageData"
  },
  "isFlippedHorizontal": false,
  "isFlippedVertical": false,
  "isLocked": false,
  "isVisible": true,
  "layerListExpandedType": 0,
  "name": "icons8-finland",
  "nameIsFixed": false,
  "nineSliceCenterRect": "{{0, 0}, {0, 0}}",
  "nineSliceScale": "{0, 0}",
  "resizingConstraint": 63,
  "resizingType": 0,
  "rotation": 0,
  "shouldBreakMaskChain": false,
  "style": {
    "_class": "style",
    "borders": [
      {
        "_class": "border",
        "color": {
          "_class": "color",
          "alpha": 1,
          "blue": 1,
          "green": 0.7098039215686274,
          "red": 0.2980392156862746
        },
        "fillType": 0,
        "isEnabled": true,
        "position": 0,
        "thickness": 2
      }
    ],
    "endDecorationType": 0,
    "miterLimit": 10,
    "startDecorationType": 0
  }
}